typedoc/__init__.py
typedoc/plugin.py
mkdocs_typedoc-1.0.4.dist-info/LICENSE
mkdocs_typedoc-1.0.4.dist-info/METADATA
mkdocs_typedoc-1.0.4.dist-info/WHEEL
mkdocs_typedoc-1.0.4.dist-info/entry_points.txt
mkdocs_typedoc-1.0.4.dist-info/top_level.txt
mkdocs_typedoc-1.0.4.dist-info/RECORD
