Metadata-Version: 2.1
Name: mkdocs-typedoc
Version: 1.0.4
Summary: MkDocs plugin to generate documentation from TypeScript source code using TypeDoc.
Home-page: https://github.com/JakubAndrysek/mkdocs-typedoc
Author: Jakub Andrýsek
Author-email: email@kubaandrysek.cz
License: MIT
Project-URL: Source, https://github.com/JakubAndrysek/mkdocs-typedoc
Project-URL: Documentation, https://typedoc.kubaandrysek.cz/
Project-URL: Tracker, https://github.com/JakubAndrysek/mkdocs-typedoc/issues
Project-URL: Funding, https://github.com/sponsors/jakubandrysek
Keywords: mkdocs plugin
Classifier: License :: OSI Approved :: MIT License
Classifier: Programming Language :: Python :: 3.7
Classifier: Programming Language :: Python :: 3.8
Classifier: Programming Language :: Python :: 3.9
Classifier: Programming Language :: Python :: 3.10
Classifier: Programming Language :: Python :: 3.11
Classifier: Programming Language :: Python :: 3.12
Classifier: Operating System :: OS Independent
Requires-Python: >=3.7
License-File: LICENSE
Requires-Dist: mkdocs
Provides-Extra: dev
Requires-Dist: mkdocs-material ; extra == 'dev'
Requires-Dist: mkdocs-open-in-new-tab ; extra == 'dev'
Requires-Dist: mkdocs-glightbox ; extra == 'dev'
Requires-Dist: mkdocs-git-revision-date-localized-plugin ; extra == 'dev'
